sdre/.version
sdre/__init__.py
sdre/func.py
sdre/infer.py
sdre/model.py
sdre/test.py
sdre/utils.py
sdre-0.0.4.dist-info/METADATA
sdre-0.0.4.dist-info/WHEEL
sdre-0.0.4.dist-info/top_level.txt
sdre-0.0.4.dist-info/RECORD
