Metadata-Version: 2.1
Name: sdre
Version: 0.0.4
Summary: sdre - Stochastic Divison Rate Estimation
Author-email: "Richard D. Paul" <r.paul@fz-juelich.de>
License: MIT License
Project-URL: homepage, https://jugit.fz-juelich.de/ias-8/sdre
Classifier: Programming Language :: Python :: 3
Classifier: Operating System :: OS Independent
Requires-Python: >=3.7
Requires-Dist: numpy <1.24
Requires-Dist: sdre-cpp
